{
  "node_id": 0,
  "chain_id": 168,
  "block_size": 10000,
  "tx_pool_size" : 100,
  "storage_root_path": "/root/temp_db",
  "drop_database" : true,
  "input_dataset_path": "/root/banknote-chain-dataset/token_transfers1y_usdt_sorted.csv",
  "output_dataset_path": "/root/outputData/output_tps_origin_100.csv",
  "cache_size": 128,
  "tx_generator_mode": "csv",
  "peer_count": 4,
  "is_proposer" : true,
  "proposer_address" :"/ip4/47.238.136.192/tcp/16661",
  "p2p_sender_listen_address": "/ip4/0.0.0.0/tcp/16661",
  "p2p_sender_id_file_path" : "./publisher_key",
  "p2p_topic":"fwcyfyl",
  "banknote_chain_pledger_number": 16,
  "p_account_modify_chan_size": 1000,
  "work_number_per_pledger": 8,
  "pledger_inner_chan_size": 1000,
  "tx_count_per_block": 100,
  "node_mode": "peer",
  "exp_mode": "origin",
  "usdt_dataset_path":"/root/banknote-chain-dataset/token_transfers1y_usdt_sorted.csv",
  "banknote_dataset_path":"/root/banknote-chain-dataset/tx_16_164.csv",
  "block_interval": 2000,
  "exp_block_number": 100,
  "core_limit": 64,
  "debug_mode":false
}
